bblocks/places/__init__.py
bblocks/places/concordance.csv
bblocks/places/concordance.py
bblocks/places/config.py
bblocks/places/disambiguator.py
bblocks/places/main.py
bblocks/places/resolver.py
bblocks/places/utils.py
bblocks_places-0.0.4.dist-info/METADATA
bblocks_places-0.0.4.dist-info/WHEEL
bblocks_places-0.0.4.dist-info/licenses/LICENSE
bblocks_places-0.0.4.dist-info/RECORD
