Metadata-Version: 2.4
Name: bblocks-places
Version: 0.0.4
Summary: Resolve and standardize places and work with political and geographic groupings
License: MIT
License-File: LICENSE
Author: ONE Campaign
Requires-Python: >=3.11,<4.0
Classifier: License :: OSI Approved :: MIT License
Classifier: Programming Language :: Python :: 3
Classifier: Programming Language :: Python :: 3.11
Classifier: Programming Language :: Python :: 3.12
Classifier: Programming Language :: Python :: 3.13
Classifier: Programming Language :: Python :: 3.14
Requires-Dist: chardet (>=5.2.0,<6.0.0)
Requires-Dist: charset-normalizer (>=3.4.2,<4.0.0)
Requires-Dist: datacommons-client (>=2.0.0,<3.0.0)
Requires-Dist: pandas (>=2.2.3,<3.0.0)
Project-URL: Documentation, https://docs.one.org/tools/bblocks/places/
Project-URL: Homepage, https://docs.one.org/tools/bblocks/places/
Project-URL: Repository, https://github.com/ONEcampaign/bblocks-places
